{"data":{"site":{"siteMetadata":{"disqusShortname":"roofox-dev"}},"markdownRemark":{"id":"ec9ef82d-087b-5263-b42c-f1ed3dcd2c80","excerpt":"¡Esta es mi primera publicación en roofox.dev! Estoy seguro que escribiré cosas mas interesantes en el futuro. 🤔","html":"<p>¡Esta es mi primera publicación en roofox.dev!</p>\n<p>Estoy seguro que escribiré cosas mas interesantes en el futuro. 🤔</p>","frontmatter":{"title":"Hello World","date":"May 01, 2015","description":"Hello World"}}},"pageContext":{"slug":"/hello-world/","previous":null,"next":{"fields":{"slug":"/nginx-docker-first-version/"},"frontmatter":{"title":"URLs amigables utilizando NGINX y docker","date":"2018-12-04T21:31:00.000Z","description":"Hello World","path":"/nginx-docker-first-version/","cover":"cc9a"}},"cover":"7cfc"}}